django_cloud_deploy/__init__.py
django_cloud_deploy/__version__.py
django_cloud_deploy/config.py
django_cloud_deploy/django_cloud_deploy.py
django_cloud_deploy/nox.py
django_cloud_deploy/tool_requirements.py
django_cloud_deploy/cli/__init__.py
django_cloud_deploy/cli/cloudify.py
django_cloud_deploy/cli/io.py
django_cloud_deploy/cli/new.py
django_cloud_deploy/cli/prompt.py
django_cloud_deploy/cli/update.py
django_cloud_deploy/cloudlib/__init__.py
django_cloud_deploy/cloudlib/auth.py
django_cloud_deploy/cloudlib/billing.py
django_cloud_deploy/cloudlib/cloud_source.py
django_cloud_deploy/cloudlib/cloudbuild.py
django_cloud_deploy/cloudlib/container.py
django_cloud_deploy/cloudlib/database.py
django_cloud_deploy/cloudlib/enable_service.py
django_cloud_deploy/cloudlib/project.py
django_cloud_deploy/cloudlib/service_account.py
django_cloud_deploy/cloudlib/static_content_serve.py
django_cloud_deploy/cloudlib/data/cluster_definition.json
django_cloud_deploy/crash_handling/__init__.py
django_cloud_deploy/crash_handling/template/issue_template.txt
django_cloud_deploy/skeleton/__init__.py
django_cloud_deploy/skeleton/__main__.py
django_cloud_deploy/skeleton/requirements_parser.py
django_cloud_deploy/skeleton/source_generator.py
django_cloud_deploy/skeleton/utils.py
django_cloud_deploy/skeleton/templates/.dockerignore
django_cloud_deploy/skeleton/templates/.gcloudignore
django_cloud_deploy/skeleton/templates/Dockerfile
django_cloud_deploy/skeleton/templates/app.yaml
django_cloud_deploy/skeleton/templates/main.py-tpl
django_cloud_deploy/skeleton/templates/project_name.yaml
django_cloud_deploy/skeleton/templates/requirements-google.txt
django_cloud_deploy/skeleton/templates/requirements.txt
django_cloud_deploy/skeleton/templates/app_template/__init__.py-tpl
django_cloud_deploy/skeleton/templates/app_template/admin.py-tpl
django_cloud_deploy/skeleton/templates/app_template/apps.py-tpl
django_cloud_deploy/skeleton/templates/app_template/models.py-tpl
django_cloud_deploy-0.3.4.dist-info/LICENSE
django_cloud_deploy-0.3.4.dist-info/METADATA
django_cloud_deploy-0.3.4.dist-info/WHEEL
django_cloud_deploy-0.3.4.dist-info/entry_points.txt
django_cloud_deploy-0.3.4.dist-info/top_level.txt
django_cloud_deploy-0.3.4.dist-info/RECORD
