Metadata-Version: 2.1
Name: django-cloud-deploy
Version: 0.3.4
Summary: Tool to deploy a Django App onto GCP
Home-page: https://github.com/GoogleCloudPlatform/django-cloud-deploy
Author: Django Deploy Team
License: Apache 2.0
Keywords: google django cloud
Platform: UNKNOWN
Classifier: Programming Language :: Python :: 3.5
Classifier: Programming Language :: Python :: 3.6
Classifier: Development Status :: 3 - Alpha
Classifier: Intended Audience :: Developers
Classifier: License :: OSI Approved :: Apache Software License
Classifier: Operating System :: Unix
Classifier: Intended Audience :: Developers
Requires-Python: >=3.5
Requires-Dist: urllib3 (<1.25,>=1.23)
Requires-Dist: oauth2client (>=4.1.2)
Requires-Dist: django (>=2.1.5)
Requires-Dist: backoff (>=1.8.0)
Requires-Dist: jinja2 (>=2.10)
Requires-Dist: docker (>=3.4.1)
Requires-Dist: kubernetes (>=6.0.0)
Requires-Dist: grpcio (>=1.14.1)
Requires-Dist: pexpect (>=4.6.0)
Requires-Dist: google-api-python-client (>=1.7.4)
Requires-Dist: google-auth-httplib2 (>=0.0.3)
Requires-Dist: progressbar2 (>=3.38.0)
Requires-Dist: portpicker (>=1.2.0)
Requires-Dist: PyYAML (>=5.1)
Provides-Extra: test
Requires-Dist: absl-py (>=0.7.1) ; extra == 'test'
Requires-Dist: nox ; extra == 'test'
Requires-Dist: nox-automation (>=0.19.1) ; extra == 'test'
Requires-Dist: selenium (>=3.141.0) ; extra == 'test'
